yoti_python_sandbox/__init__.py
yoti_python_sandbox/age_verification.py
yoti_python_sandbox/anchor.py
yoti_python_sandbox/attribute.py
yoti_python_sandbox/client.py
yoti_python_sandbox/endpoint.py
yoti_python_sandbox/sandbox_exception.py
yoti_python_sandbox/token.py
yoti_python_sandbox/version.py
yoti_python_sandbox/doc_scan/__init__.py
yoti_python_sandbox/doc_scan/check_reports.py
yoti_python_sandbox/doc_scan/client.py
yoti_python_sandbox/doc_scan/document_filter.py
yoti_python_sandbox/doc_scan/response_config.py
yoti_python_sandbox/doc_scan/task_results.py
yoti_python_sandbox/doc_scan/check/__init__.py
yoti_python_sandbox/doc_scan/check/sandbox_check.py
yoti_python_sandbox/doc_scan/check/sandbox_check_report.py
yoti_python_sandbox/doc_scan/check/sandbox_check_result.py
yoti_python_sandbox/doc_scan/check/sandbox_document_authenticity_check.py
yoti_python_sandbox/doc_scan/check/sandbox_document_check.py
yoti_python_sandbox/doc_scan/check/sandbox_document_face_match_check.py
yoti_python_sandbox/doc_scan/check/sandbox_document_text_data_check.py
yoti_python_sandbox/doc_scan/check/sandbox_id_document_comparison_check.py
yoti_python_sandbox/doc_scan/check/sandbox_liveness_check.py
yoti_python_sandbox/doc_scan/check/sandbox_supplementary_document_text_data_check.py
yoti_python_sandbox/doc_scan/check/sandbox_zoom_liveness_check.py
yoti_python_sandbox/doc_scan/check/report/__init__.py
yoti_python_sandbox/doc_scan/check/report/breakdown.py
yoti_python_sandbox/doc_scan/check/report/detail.py
yoti_python_sandbox/doc_scan/check/report/recommendation.py
yoti_python_sandbox/doc_scan/exception/__init__.py
yoti_python_sandbox/doc_scan/exception/doc_scan_sandbox_exception.py
yoti_python_sandbox/doc_scan/task/__init__.py
yoti_python_sandbox/doc_scan/task/sandbox_supplementary_document_text_extraction_task.py
yoti_python_sandbox/doc_scan/task/sandbox_text_extraction_reason.py
yoti_python_sandbox/doc_scan/task/sandbox_text_extraction_recommendation.py
yoti_sandbox-1.3.0.dist-info/LICENSE
yoti_sandbox-1.3.0.dist-info/METADATA
yoti_sandbox-1.3.0.dist-info/WHEEL
yoti_sandbox-1.3.0.dist-info/top_level.txt
yoti_sandbox-1.3.0.dist-info/RECORD
