Metadata-Version: 2.1
Name: yoti-sandbox
Version: 1.3.0
Summary: The Yoti Python Sandbox SDK, providing API support for sandbox services
Home-page: https://github.com/getyoti/yoti-python-sdk-sandbox
Author: Yoti
Author-email: websdk@yoti.com
License: MIT
Keywords: yoti sdk 2FA multifactor authentication verification identity login register verify 2Factor sandbox
Platform: UNKNOWN
Classifier: Development Status :: 5 - Production/Stable
Classifier: License :: OSI Approved :: MIT License
Classifier: Operating System :: OS Independent
Classifier: Intended Audience :: Developers
Classifier: Programming Language :: Python
Classifier: Programming Language :: Python :: 3
Classifier: Programming Language :: Python :: 3.6
Classifier: Programming Language :: Python :: 3.7
Classifier: Programming Language :: Python :: 3.8
Classifier: Topic :: Software Development :: Libraries :: Python Modules
Requires-Dist: yoti (>=2.12.0)
Requires-Dist: cryptography (>=2.8.0)
Provides-Extra: dev
Requires-Dist: pre-commit (==2.8.1) ; extra == 'dev'
Requires-Dist: pytest (>=4.6.0) ; extra == 'dev'
Requires-Dist: pytest-cov (>=2.7.1) ; extra == 'dev'
Requires-Dist: pylint (==2.6.0) ; extra == 'dev'
Requires-Dist: pylint-exit (>=1.1.0) ; extra == 'dev'
Requires-Dist: python-coveralls (==2.9.3) ; extra == 'dev'
Requires-Dist: coverage (==5.3) ; extra == 'dev'
Requires-Dist: mock (==4.0.2) ; extra == 'dev'
Requires-Dist: virtualenv (==20.1.0) ; extra == 'dev'
